[
  {
    "hash": "0f1f46094c0e6266fe9fc768f0edf73c93c3071e",
    "short": "0f1f460",
    "message": "feat: reinforce experience overlays and add dunes palette",
    "date": "2026-01-07T22:14:06+01:00"
  },
  {
    "hash": "9eaf5ae11c2ed43415fe37bc614b5b1d366ebd6f",
    "short": "9eaf5ae",
    "message": "chore: refresh commit log",
    "date": "2026-01-07T22:07:07+01:00"
  },
  {
    "hash": "aeabf1f0b04cbe21a02c5e17933ed8a714d4ade0",
    "short": "aeabf1f",
    "message": "feat: enrich experience overlays on CTA click",
    "date": "2026-01-07T22:06:55+01:00"
  },
  {
    "hash": "50099e2d993987ffdf3fad057a88dc32296cb8db",
    "short": "50099e2",
    "message": "chore: refresh commit log",
    "date": "2026-01-07T22:02:51+01:00"
  },
  {
    "hash": "592df43a91c9b14ab1726f22da87c6faa96043cc",
    "short": "592df43",
    "message": "fix: keep store carousels fully in frame",
    "date": "2026-01-07T22:02:42+01:00"
  },
  {
    "hash": "647de374fe0ec2a411914e842ab4396e6e758cef",
    "short": "647de37",
    "message": "chore: refresh commit log",
    "date": "2026-01-07T22:00:23+01:00"
  },
  {
    "hash": "c71a80d298eb5c2a770943a2a0663089a04848df",
    "short": "c71a80d",
    "message": "fix: enforce five-wide store carousel",
    "date": "2026-01-07T22:00:17+01:00"
  },
  {
    "hash": "4ea88eaa49cf4e9075c1a8621404758a94a2c998",
    "short": "4ea88ea",
    "message": "chore: refresh commit log",
    "date": "2026-01-07T21:54:55+01:00"
  },
  {
    "hash": "ea9be113ee78099441f5dbf1333457735d3d25f1",
    "short": "ea9be11",
    "message": "chore: show five store items at once",
    "date": "2026-01-07T21:54:47+01:00"
  },
  {
    "hash": "b706f6f24e1252eb02c404e1746ce4d98bbde574",
    "short": "b706f6f",
    "message": "chore: refresh commit log",
    "date": "2026-01-07T21:51:57+01:00"
  }
]
